junkdrawer/__init__.py
junkdrawer/arg_parser.py
junkdrawer/dict_vs_list_vs_dataclass_vs_slots.py
junkdrawer/func_io_monitor.py
junkdrawer/json_data_struct_filter.py
junkdrawer/log.py
junkdrawer/nested_dict_access_by_key_list.py
junkdrawer/flask_skeleton/__init__.py
junkdrawer/flask_skeleton/flask_skeleton/__init__.py
junkdrawer/flask_skeleton/flask_skeleton/database/__init__.py
junkdrawer/flask_skeleton/flask_skeleton/database/db.py
junkdrawer/flask_skeleton/flask_skeleton/rest_api/__init__.py
junkdrawer/flask_skeleton/flask_skeleton/rest_api/endpoints_1.py
junkdrawer/flask_skeleton/flask_skeleton/scripts/__init__.py
junkdrawer/flask_skeleton/flask_skeleton/scripts/start_flask_app.py
junkdrawer/flask_skeleton/flask_skeleton/tests/__init__.py
junkdrawer/flask_skeleton/flask_skeleton/tests/conftest.py
junkdrawer-0.0.1.dist-info/LICENSE
junkdrawer-0.0.1.dist-info/METADATA
junkdrawer-0.0.1.dist-info/WHEEL
junkdrawer-0.0.1.dist-info/top_level.txt
junkdrawer-0.0.1.dist-info/RECORD
