Metadata-Version: 2.1
Name: junkdrawer
Version: 0.0.1
Summary: Useful Python utilities and patterns for a career Python developer.
Home-page: https://github.com/elegantmoose/junkdrawer
License: MIT
Platform: UNKNOWN
Requires-Dist: flask
Requires-Dist: gunicorn
Requires-Dist: pympler
Requires-Dist: pytest
Requires-Dist: pyyaml
